choreo/__init__.py
choreo/__main__.py
tests/__init__.py
choreo-0.0.1.dist-info/LICENSE
choreo-0.0.1.dist-info/METADATA
choreo-0.0.1.dist-info/WHEEL
choreo-0.0.1.dist-info/entry_points.txt
choreo-0.0.1.dist-info/top_level.txt
choreo-0.0.1.dist-info/RECORD
